boolean_switch.v
module boolean_switch(
    input A, B, C, D,
    output Y
);

    wire n1, n2, n3, n4, Vdd, Gnd;
    assign Vdd = 1'b1;
    assign Gnd = 1'b0;

    // n1 = B + C (OR gate using transmission gate logic)
    wire notB, notC, nor_out;
    not (notB, B);
    not (notC, C);
    and (nor_out, notB, notC);
    not (n1, nor_out); // n1 = B + C

    // n2 = A & (B + C)
    and (n2, A, n1);

    // n3 = A & C
    and (n3, A, C);

    // n4 = A·C·D
    and (n4, n3, D);

    // Y = n2 + n4
    or (Y, n2, n4);

endmodule

boolean_switch_tb.v
`timescale 1ns/1ps
module boolean_switch_tb;

    reg A, B, C, D;
    wire Y;

    // Instantiate the module under test
    boolean_switch uut (
        .A(A),
        .B(B),
        .C(C),
        .D(D),
        .Y(Y)
    );

    initial begin
        $dumpfile("boolean_switch.vcd");
        $dumpvars(0, boolean_switch_tb);

        // Apply all 16 combinations of A, B, C, D
        A = 0; B = 0; C = 0; D = 0;
        repeat (16) begin
            #10 {A, B, C, D} = {A, B, C, D} + 1;
        end

        #10 $finish;
    end

endmodule

boolean_switch.vcd
$date
	Thu Apr 17 13:35:49 2025
$end
$version
	Icarus Verilog
$end
$timescale
	1ps
$end
$scope module boolean_switch_tb $end
$var wire 1 ! Y $end
$var reg 1 " A $end
$var reg 1 # B $end
$var reg 1 $ C $end
$var reg 1 % D $end
$scope module uut $end
$var wire 1 " A $end
$var wire 1 # B $end
$var wire 1 $ C $end
$var wire 1 % D $end
$var wire 1 & Gnd $end
$var wire 1 ' Vdd $end
$var wire 1 ! Y $end
$var wire 1 ( n1 $end
$var wire 1 ) n2 $end
$var wire 1 * n3 $end
$var wire 1 + n4 $end
$var wire 1 , nor_out $end
$var wire 1 - notB $end
$var wire 1 . notC $end
$upscope $end
$upscope $end
$enddefinitions $end
$comment Show the parameter values. $end
$dumpall
$end
#0
$dumpvars
1.
1-
1,
0+
0*
0)
0(
1'
0&
0%
0$
0#
0"
0!
$end
#10000
1%
#20000
1(
0,
0.
1$
0%
#30000
1%
#40000
0-
1.
1#
0$
0%
#50000
1%
#60000
0.
1$
0%
#70000
1%
#80000
0(
0!
1,
0)
1-
1.
1"
0#
0$
0%
#90000
1%
#100000
1!
1)
1(
0,
0.
1*
1$
0%
#110000
1+
1%
#120000
0-
1.
0*
0+
1#
0$
0%
#130000
1%
#140000
0.
1*
1$
0%
#150000
1+
1%
#160000
0(
1,
0!
0)
1-
1.
0*
0+
0"
0#
0$
0%
