switch_level_logic.v
module switch_level_logic (
    input a, b, c, d,  // Inputs
    output y           // Output
);

    wire ab, cd;       // Intermediate wires for AND results

    // Transmission gate for AND operation ab
    nmos n1(ab, a, b);  // NMOS for AND (ab)
    pmos p1(ab, a, b);  // PMOS for AND (ab)

    // Transmission gate for AND operation cd
    nmos n2(cd, c, d);  // NMOS for AND (cd)
    pmos p2(cd, c, d);  // PMOS for AND (cd)

    // OR operation using transmission gates
    wire y1, y2;
    nmos n3(y1, ab, 1'b1);  // NMOS for OR (ab or cd)
    pmos p3(y1, ab, 1'b1);  // PMOS for OR (ab or cd)
    
    nmos n4(y2, cd, 1'b1);  // NMOS for OR (ab or cd)
    pmos p4(y2, cd, 1'b1);  // PMOS for OR (ab or cd)

    assign y = y1 | y2;     // Final output y

endmodule

test_switch_level_logic.v
module test_switch_level_logic;

    reg a, b, c, d;        // Inputs
    wire y;                // Output

    // Instantiate the switch-level logic module
    switch_level_logic uut (
        .a(a),
        .b(b),
        .c(c),
        .d(d),
        .y(y)
    );

    initial begin
        // VCD (waveform) dump setup
        $dumpfile("waveform.vcd");               // Create VCD file
        $dumpvars(0, test_switch_level_logic);   // Dump all variables in this module

        // Apply test vectors
        $monitor("a=%b, b=%b, c=%b, d=%b, y=%b", a, b, c, d, y);
        
        // Test cases
        a = 0; b = 0; c = 0; d = 0; #10;
        a = 1; b = 0; c = 0; d = 0; #10;
        a = 0; b = 1; c = 0; d = 0; #10;
        a = 0; b = 0; c = 1; d = 0; #10;
        a = 0; b = 0; c = 0; d = 1; #10;
        a = 1; b = 1; c = 0; d = 0; #10;
        a = 0; b = 0; c = 1; d = 1; #10;
        a = 1; b = 1; c = 1; d = 1; #10;

        $finish;
    end
endmodule

waveform.vcd
$date
	Thu Apr 17 13:47:45 2025
$end
$version
	Icarus Verilog
$end
$timescale
	1s
$end
$scope module test_switch_level_logic $end
$var wire 1 ! y $end
$var reg 1 " a $end
$var reg 1 # b $end
$var reg 1 $ c $end
$var reg 1 % d $end
$scope module uut $end
$var wire 1 " a $end
$var wire 1 & ab $end
$var wire 1 # b $end
$var wire 1 $ c $end
$var wire 1 ' cd $end
$var wire 1 % d $end
$var wire 1 ! y $end
$var wire 1 ( y1 $end
$var wire 1 ) y2 $end
$upscope $end
$upscope $end
$enddefinitions $end
$comment Show the parameter values. $end
$dumpall
$end
#0
$dumpvars
0)
0(
0'
0&
0%
0$
0#
0"
0!
$end
#10
1!
1(
1&
1"
#20
0!
1#
0(
0&
0"
#30
1!
1)
1'
1$
0#
#40
0!
1%
0)
0'
0$
#50
1!
0%
1#
1(
1&
1"
#60
1%
1)
1'
1$
0#
0(
0&
0"
#70
1#
1(
1&
1"
